Queue.py
Stack.py
__init__.py
bsoup_util.py
cli_util.py
cmd_util.py
collection_util.py
concurrent_util.py
context_util.py
cron_util.py
curl_util.py
date_util.py
dingding_util.py
download_util.py
email_util.py
encrypt_util.py
excel_util.py
file_util.py
flask_util.py
ftp_util.py
http_util.py
import_util.py
influxdb_util.py
io_util.py
json_util.py
log_util.py
mongodb_util.py
mysql_util.py
object_util.py
pandas_util.py
pool_util.py
progress_util.py
pub_sub_server.py
pymysql_util.py
records_util.py
redis_mq_util.py
redis_util.py
request_util.py
schedule_util.py
sqlite_util.py
ssh_util.py
string_util.py
tablib_util.py
url_util.py
xlsx_util.py
nylib-1.0.dist-info/METADATA
nylib-1.0.dist-info/WHEEL
nylib-1.0.dist-info/top_level.txt
nylib-1.0.dist-info/RECORD
